forerunner/__init__.py
forerunner/app.py
forerunner/cli.py
forerunner/console.py
forerunner/module.py
forerunner/server.py
forerunner/utils.py
forerunner/dependency/depends.py
forerunner/dependency/utils.py
forerunner/job/__init__.py
forerunner/job/base.py
forerunner/job/cron.py
forerunner/job/sub.py
forerunner/queue/__init__.py
forerunner/queue/queue.py
forerunner-0.0.8.dist-info/METADATA
forerunner-0.0.8.dist-info/WHEEL
forerunner-0.0.8.dist-info/entry_points.txt
forerunner-0.0.8.dist-info/RECORD
