Metadata-Version: 2.1
Name: forerunner
Version: 0.0.8
Requires-Python: >=3.10.4
Requires-Dist: click~=8.1.3
Requires-Dist: croniter~=1.3.7
Requires-Dist: prometheus-client~=0.16.0
Requires-Dist: rich~=13.3.2
Requires-Dist: structlog~=22.3.0
Requires-Dist: uvicorn~=0.22.0
